pygator/__init__.py
pygator/_version.py
pygator/ABCD/__init__.py
pygator/ABCD/multimatrix.py
pygator/beam_profile/Live_Phase_Maps.py
pygator/beam_profile/__init__.py
pygator/beam_profile/beam_profile_fit.py
pygator/beam_profile/fit_gaussian.py
pygator/beam_profile/get_camera_model.py
pygator/beam_profile/live_camera.py
pygator/beam_profile/live_camera_fit.py
pygator/beam_profile/live_visualize_beam.py
pygator/finesse/__init__.py
pygator/finesse/cavities_mm.py
pygator/library/__init__.py
pygator/library/materials.py
pygator/module/__init__.py
pygator/module/module.py
pygator/spectran/__init__.py
pygator/spectran/fft_analysis.py
pygator/spectran/welch_analysis.py
pygator-1.1.6.dist-info/METADATA
pygator-1.1.6.dist-info/WHEEL
pygator-1.1.6.dist-info/top_level.txt
pygator-1.1.6.dist-info/RECORD
