Metadata-Version: 2.4
Name: pygator
Version: 1.1.6
Summary: A collection of functions useful for Gaussian optics.
Home-page: https://github.com/DiabRaed/pygator
Author: Raed Diab
Author-email: Raed Diab <contact@raeddiab.com>
Project-URL: Homepage, https://github.com/DiabRaed/pygator
Project-URL: Bug Tracker, https://github.com/DiabRaed/pygator/issues
Keywords: LIGO,LISA,optics,laser,UF
Requires-Dist: numpy>=1.24
Requires-Dist: matplotlib>=3.6
Requires-Dist: scipy>=1.10
Requires-Dist: opencv-python
Dynamic: author
Dynamic: home-page
